{
  "relation_id": "宋集薪->许弱",
  "source_name": "宋集薪",
  "target_name": "许弱",
  "primary_action": "同行",
  "action_types": [
    "同行",
    "对话"
  ],
  "interaction_count": 2,
  "progress_start": 7726,
  "progress_end": 7753,
  "source_units": [
    255,
    256
  ],
  "contexts": [
    "少女名为稚圭，她低眉顺眼跟在自家公子“宋集薪”身后，从头到尾，少女都没有看苻畦一眼，可能是苻畦没有身穿老龙袍，加上这位老龙城城主也没有如何自报名号，与剑仙许弱一起站在船头寒暄客套起来，所以她没有认出？",
    "剑仙许弱也不知所踪，这个人，据说在中土神洲都有偌大名头的墨家豪侠，宋集薪一直想要结交示好，但是总觉得对谁都和颜悦色的许弱，其实最不好说话，双方很难交心，也许哪天等自己走到那个位置上，才会好一些？"
  ],
  "shared_event_refs": [
    {
      "event_id": "第四卷剑气近 第二百五十四章 精诚动人也伤人 · 稚圭与宋集薪在大骊对话@255",
      "name": "第四卷剑气近 第二百五十四章 精诚动人也伤人 · 稚圭与宋集薪在大骊对话",
      "description": "两人护送之人，是一对少年少女，准确说来，是大骊皇子宋睦一人。",
      "significance": "在大骊推动稚圭与宋集薪之间的对话线。",
      "location": "大骊",
      "source_units": [
        255
      ],
      "phase": "early"
    },
    {
      "event_id": "第四卷剑气近 第二百五十五章 传道人传道 · 许弱与宋集薪在小镇遭遇@256",
      "name": "第四卷剑气近 第二百五十五章 传道人传道 · 许弱与宋集薪在小镇遭遇",
      "description": "宋集薪一路上遇见了不少俊朗男子和丫鬟婢女，没有人知道他的身份，只不过宋集薪腰间的那对老龙翻云佩和老龙布雨佩，足够让他在苻家畅通无阻。今天稚圭又不知道跑到哪里去玩了。",
      "significance": "在小镇推动许弱与宋集薪之间的遭遇线。",
      "location": "小镇",
      "source_units": [
        256
      ],
      "phase": "late"
    }
  ],
  "action_type_counts": {
    "同行": 1,
    "对话": 1
  },
  "contexts_by_phase": {
    "early": [
      "少女名为稚圭，她低眉顺眼跟在自家公子“宋集薪”身后，从头到尾，少女都没有看苻畦一眼，可能是苻畦没有身穿老龙袍，加上这位老龙城城主也没有如何自报名号，与剑仙许弱一起站在船头寒暄客套起来，所以她没有认出？"
    ],
    "late": [
      "剑仙许弱也不知所踪，这个人，据说在中土神洲都有偌大名头的墨家豪侠，宋集薪一直想要结交示好，但是总觉得对谁都和颜悦色的许弱，其实最不好说话，双方很难交心，也许哪天等自己走到那个位置上，才会好一些？"
    ]
  },
  "input_hash": "83d2115a8e6bef66f7535d5eecad85218d9d6e00898b667ef42218b4ba4d0ab4"
}