{
  "relation_id": "崔明皇->陈对",
  "source_name": "崔明皇",
  "target_name": "陈对",
  "primary_action": "对话",
  "action_types": [
    "对话"
  ],
  "interaction_count": 1,
  "progress_start": 1241,
  "progress_end": 1241,
  "source_units": [
    50
  ],
  "contexts": [
    "然后崔明皇望向名叫陈对的女子，关心问道：“陈姑娘你没事吧？"
  ],
  "shared_event_refs": [
    {
      "event_id": "第一卷笼中雀 第五十章 天行健 · 崔明皇与陈对对话@50",
      "name": "第一卷笼中雀 第五十章 天行健 · 崔明皇与陈对对话",
      "description": "崔明皇摇头道：“围棋当中，同样是九段国手，也分强弱，相差很大，何况宋长镜本就是第九境里的最强手。 然后崔明皇望向名叫陈对的女子，关心问道：“陈姑娘你没事吧？ ”",
      "significance": "推动崔明皇与陈对之间的对话关系。",
      "location": null,
      "source_units": [
        50
      ],
      "phase": "early"
    }
  ],
  "action_type_counts": {
    "对话": 1
  },
  "contexts_by_phase": {
    "early": [
      "然后崔明皇望向名叫陈对的女子，关心问道：“陈姑娘你没事吧？"
    ]
  },
  "input_hash": "c67658fda59f4cfc3fa2a0283ddd42aa953f16353b41c6f6c13a606cec7a49dc"
}