{
  "relation_id": "李槐->石春嘉",
  "source_name": "李槐",
  "target_name": "石春嘉",
  "primary_action": "别离",
  "action_types": [
    "别离",
    "同行"
  ],
  "interaction_count": 2,
  "progress_start": 3821,
  "progress_end": 6988,
  "source_units": [
    141,
    236
  ],
  "contexts": [
    "李槐满脸得意洋洋，从油纸袋里抽出一张折叠整齐的纸张，解释道：“当初学塾里不断有人离开，最后只剩下我、李宝瓶、林守一、石春嘉和董水井五个，先生在最后一堂课，给了我们一人一张字帖，上头就写了一个齐字，要我们用心临摹，说是功课。",
    "当初他，李宝瓶，林守一，李槐，石春嘉，五个学塾弟子，一起把真实身份是大骊死士的车夫，骗得团团转，虽说出谋划策和查漏补缺的是李宝瓶和林守一，但事实上任何一个人，只要露出丝毫马脚，就会前功尽弃，所以最终正式成为齐静春嫡传弟子的五个孩子，没有一个是省油的灯。"
  ],
  "shared_event_refs": [],
  "action_type_counts": {
    "别离": 1,
    "同行": 1
  },
  "contexts_by_phase": {
    "early": [
      "李槐满脸得意洋洋，从油纸袋里抽出一张折叠整齐的纸张，解释道：“当初学塾里不断有人离开，最后只剩下我、李宝瓶、林守一、石春嘉和董水井五个，先生在最后一堂课，给了我们一人一张字帖，上头就写了一个齐字，要我们用心临摹，说是功课。"
    ],
    "late": [
      "当初他，李宝瓶，林守一，李槐，石春嘉，五个学塾弟子，一起把真实身份是大骊死士的车夫，骗得团团转，虽说出谋划策和查漏补缺的是李宝瓶和林守一，但事实上任何一个人，只要露出丝毫马脚，就会前功尽弃，所以最终正式成为齐静春嫡传弟子的五个孩子，没有一个是省油的灯。"
    ]
  },
  "input_hash": "c1566f561f640a40db76c8aabb5d44618d557350357e045d6b24934d93dcb52d"
}